pynogram/__init__.py
pynogram/__main__.py
pynogram/__version__.py
pynogram/animation.py
pynogram/reader.py
pynogram/core/__init__.py
pynogram/core/backtracking.py
pynogram/core/board.py
pynogram/core/color.py
pynogram/core/common.py
pynogram/core/propagation.py
pynogram/core/renderer.py
pynogram/core/line/__init__.py
pynogram/core/line/base.py
pynogram/core/line/bgu.py
pynogram/core/line/efficient.py
pynogram/core/line/machine.py
pynogram/core/line/simpson.py
pynogram/examples/LalaFrogKK.txt
pynogram/examples/MLP.txt
pynogram/examples/apples.txt
pynogram/examples/domino.txt
pynogram/examples/einstein.txt
pynogram/examples/football.txt
pynogram/examples/frans_faase.txt
pynogram/examples/hello.txt
pynogram/examples/lancaster.txt
pynogram/examples/p.txt
pynogram/examples/smile.txt
pynogram/examples/teal.txt
pynogram/examples/uk.txt
pynogram/examples/w.txt
pynogram/examples/winter.txt
pynogram/examples/xmas.txt
pynogram/utils/__init__.py
pynogram/utils/cache.py
pynogram/utils/fsm.py
pynogram/utils/iter.py
pynogram/utils/other.py
pynogram/utils/priority_dict.py
pynogram/web/__init__.py
pynogram/web/__main__.py
pynogram/web/app.py
pynogram/web/common.py
pynogram/web/demo.py
pynogram-0.3.1.dist-info/METADATA
pynogram-0.3.1.dist-info/RECORD
pynogram-0.3.1.dist-info/WHEEL
pynogram-0.3.1.dist-info/entry_points.txt
pynogram-0.3.1.dist-info/top_level.txt
