Metadata-Version: 2.1
Name: pynogram
Version: 0.3.1
Summary: Nonogram solver
Home-page: https://github.com/tsionyx/pynogram
Author: Ivan Ladelschikov
Author-email: tsionyx@gmail.com
License: Apache License 2.0
Download-URL: https://pypi.python.org/pypi/pynogram/0.3.1
Keywords: game,nonogram,solver
Platform: UNKNOWN
Classifier: Development Status :: 3 - Alpha
Classifier: Environment :: Console
Classifier: Environment :: Web Environment
Classifier: Intended Audience :: Developers
Classifier: Intended Audience :: Information Technology
Classifier: License :: OSI Approved :: Apache Software License
Classifier: Operating System :: OS Independent
Classifier: Programming Language :: Python
Classifier: Programming Language :: Python :: 2.7
Classifier: Programming Language :: Python :: 3
Classifier: Programming Language :: Python :: 3.5
Classifier: Programming Language :: Python :: Implementation :: CPython
Classifier: Programming Language :: Python :: Implementation :: PyPy
Classifier: Topic :: Games/Entertainment :: Puzzle Games
Provides-Extra: web
Requires-Dist: six
Requires-Dist: memoized
Requires-Dist: svgwrite
Provides-Extra: web
Requires-Dist: tornado; extra == 'web'
Provides-Extra: web
Requires-Dist: futures; ( python_version < "3.2") and extra == 'web'
